sage/apps/__init__.py
sage/apps/_version.py
sage/apps/py.typed
sage/apps/article_monitoring/README.md
sage/apps/article_monitoring/__init__.py
sage/apps/article_monitoring/operators.py
sage/apps/article_monitoring/pipeline.py
sage/apps/auto_scaling_chat/README.md
sage/apps/auto_scaling_chat/__init__.py
sage/apps/auto_scaling_chat/operators.py
sage/apps/auto_scaling_chat/pipeline.py
sage/apps/medical_diagnosis/README.md
sage/apps/medical_diagnosis/__init__.py
sage/apps/medical_diagnosis/run_diagnosis.py
sage/apps/medical_diagnosis/agents/__init__.py
sage/apps/medical_diagnosis/agents/diagnostic_agent.py
sage/apps/medical_diagnosis/agents/image_analyzer.py
sage/apps/medical_diagnosis/agents/report_generator.py
sage/apps/medical_diagnosis/config/agent_config.yaml
sage/apps/medical_diagnosis/scripts/download_lumbar_dataset.py
sage/apps/medical_diagnosis/scripts/explore_dataset.py
sage/apps/medical_diagnosis/scripts/prepare_data.py
sage/apps/medical_diagnosis/tools/__init__.py
sage/apps/medical_diagnosis/tools/knowledge_base.py
sage/apps/smart_home/README.md
sage/apps/smart_home/__init__.py
sage/apps/smart_home/operators.py
sage/apps/smart_home/pipeline.py
sage/apps/video/__init__.py
sage/apps/video/video_intelligence_pipeline.py
sage/apps/video/config/default_config.yaml
sage/apps/video/operators/__init__.py
sage/apps/video/operators/analytics.py
sage/apps/video/operators/formatters.py
sage/apps/video/operators/integrations.py
sage/apps/video/operators/perception.py
sage/apps/video/operators/preprocessing.py
sage/apps/video/operators/sinks.py
sage/apps/video/operators/sources.py
sage/apps/work_report_generator/README.md
sage/apps/work_report_generator/__init__.py
sage/apps/work_report_generator/models.py
sage/apps/work_report_generator/operators.py
sage/apps/work_report_generator/pipeline.py
isage_apps-0.2.4.dist-info/METADATA
isage_apps-0.2.4.dist-info/WHEEL
isage_apps-0.2.4.dist-info/top_level.txt
isage_apps-0.2.4.dist-info/RECORD
