Metadata-Version: 2.4
Name: isage-apps
Version: 0.2.4
Summary: SAGE Applications - Real-world AI applications built on SAGE framework
Author-email: IntelliStream Team <shuhao_zhang@hust.edu.cn>
License-Expression: MIT
Project-URL: Homepage, https://github.com/intellistream/SAGE
Project-URL: Documentation, https://intellistream.github.io/SAGE
Project-URL: Repository, https://github.com/intellistream/sage-examples
Project-URL: Issues, https://github.com/intellistream/SAGE/issues
Project-URL: Source Code, https://github.com/intellistream/sage-examples/tree/main/sage-apps
Keywords: sage,applications,ai,video-intelligence,medical-diagnosis,computer-vision,healthcare,article-monitoring,auto-scaling,smart-home,work-report,intellistream
Classifier: Development Status :: 4 - Beta
Classifier: Intended Audience :: Developers
Classifier: Intended Audience :: Science/Research
Classifier: Intended Audience :: Healthcare Industry
Classifier: Topic :: Software Development :: Libraries :: Python Modules
Classifier: Topic :: Scientific/Engineering :: Artificial Intelligence
Classifier: Topic :: Scientific/Engineering :: Image Recognition
Classifier: Topic :: Scientific/Engineering :: Medical Science Apps.
Classifier: Topic :: Multimedia :: Video
Classifier: Programming Language :: Python :: 3
Classifier: Programming Language :: Python :: 3.10
Classifier: Programming Language :: Python :: 3.11
Classifier: Programming Language :: Python :: 3.12
Requires-Python: >=3.10
Requires-Dist: isage-common>=0.2.0
Requires-Dist: isage-llm-core>=0.2.0
Requires-Dist: isage-libs>=0.2.0
Requires-Dist: pyyaml>=6.0
Requires-Dist: pillow>=10.0.0
Requires-Dist: numpy<2.3.0,>=1.26.0
Provides-Extra: video
Requires-Dist: opencv-python-headless>=4.5.0; extra == "video"
Requires-Dist: torch<3.0.0,>=2.7.0; extra == "video"
Requires-Dist: torchvision<1.0.0,>=0.22.0; extra == "video"
Requires-Dist: transformers<4.54.0,>=4.52.0; extra == "video"
Provides-Extra: medical
Requires-Dist: scikit-learn>=1.3.0; extra == "medical"
Requires-Dist: pydicom>=2.3.0; extra == "medical"
Provides-Extra: article-monitoring
Requires-Dist: beautifulsoup4>=4.9.0; extra == "article-monitoring"
Requires-Dist: requests>=2.25.0; extra == "article-monitoring"
Provides-Extra: auto-scaling
Requires-Dist: redis<6.0.0,>=5.0.0; extra == "auto-scaling"
Provides-Extra: smart-home
Requires-Dist: paho-mqtt>=1.6.0; extra == "smart-home"
Provides-Extra: work-report
Requires-Dist: jinja2>=3.0.0; extra == "work-report"
Requires-Dist: markdown>=3.3.0; extra == "work-report"
Provides-Extra: all-apps
Requires-Dist: isage-apps[article-monitoring,auto-scaling,medical,smart-home,video,work-report]; extra == "all-apps"
Provides-Extra: all
Requires-Dist: isage-apps[all-apps]; extra == "all"
Provides-Extra: dev
Requires-Dist: pytest>=7.0.0; extra == "dev"
Requires-Dist: pytest-cov>=4.0.0; extra == "dev"
Requires-Dist: black>=23.0.0; extra == "dev"
Requires-Dist: ruff==0.14.6; extra == "dev"
Requires-Dist: mypy>=1.0.0; extra == "dev"
